motormtp22peng/__init__.py
motormtp22peng/geo_construct.py
motormtp22peng/main.py
motormtp22peng/mods_my.py
motormtp22peng-0.0.39.dist-info/LICENSE
motormtp22peng-0.0.39.dist-info/METADATA
motormtp22peng-0.0.39.dist-info/WHEEL
motormtp22peng-0.0.39.dist-info/top_level.txt
motormtp22peng-0.0.39.dist-info/RECORD
